{
  "_fv": 6,
  "_type": "gui",
  "definition": {
    "type": 0,
    "width": 352,
    "height": 332,
    "renderBgLayer": true,
    "components": [
      {
        "type": "label",
        "data": {
          "text": "Bread",
          "color": {
            "value": -16777216,
            "falpha": 0.0
          },
          "name": "Bread",
          "x": 409,
          "y": 96
        }
      },
      {
        "type": "image",
        "data": {
          "image": "cheapbreadrecipe.png",
          "name": "cheapbreadrecipe.png",
          "x": 265,
          "y": 114
        }
      },
      {
        "type": "button",
        "data": {
          "text": "<--",
          "onClick": {
            "name": "Page7"
          },
          "width": 60,
          "height": 40,
          "name": "<--",
          "x": 283,
          "y": 330
        }
      },
      {
        "type": "button",
        "data": {
          "text": "Close",
          "onClick": {
            "name": "RecipeBookCloseFunction"
          },
          "width": 100,
          "height": 40,
          "name": "Close",
          "x": 373,
          "y": 330
        }
      },
      {
        "type": "button",
        "data": {
          "text": "-->",
          "width": 60,
          "height": 40,
          "name": "-->",
          "x": 499,
          "y": 330
        }
      }
    ]
  }
}